MANIFEST.in
README.rst
requirements.txt
setup.cfg
setup.py
picopore/__init__.py
picopore/__main__.py
picopore/compress.py
picopore/multiprocess.py
picopore/parse_args.py
picopore/realtime.py
picopore/rename.py
picopore/runner.py
picopore/test.py
picopore/util.py
picopore/version.py
picopore.egg-info/PKG-INFO
picopore.egg-info/SOURCES.txt
picopore.egg-info/dependency_links.txt
picopore.egg-info/desktop.ini
picopore.egg-info/entry_points.txt
picopore.egg-info/requires.txt
picopore.egg-info/top_level.txt
test/test.py