Metadata-Version: 1.1
Name: picopore
Version: 1.2.0
Summary: A tool for reducing the size of Oxford Nanopore Technologies' datasets without losing information.
Home-page: https://github.com/scottgigante/picopore
Author: Scott Gigante
Author-email: scottgigante@gmail.com
License: UNKNOWN
Keywords: nanopore,compression,hdf5,fast5,oxford,minion
Platform: UNKNOWN
Classifier: Development Status :: 4 - Beta
Classifier: Intended Audience :: Science/Research
Classifier: License :: OSI Approved :: GNU General Public License (GPL)
Classifier: Topic :: Scientific/Engineering :: Bio-Informatics
